[{"inputs":[],"payable":false,"stateMutability":"nonpayable","type":"constructor","signature":"constructor"},{"constant":false,"inputs":[{"internalType":"address","name":"_collector","type":"address"},{"internalType":"uint256","name":"_value","type":"uint256"},{"internalType":"string","name":"_originalUrl","type":"string"}],"name":"collectReward","outputs":[],"payable":false,"stateMutability":"nonpayable","type":"function","signature":"0xdb8061f9"},{"constant":false,"inputs":[{"internalType":"address","name":"_requester","type":"address"},{"internalType":"uint256","name":"_value","type":"uint256"},{"internalType":"string","name":"_originalUrl","type":"string"}],"name":"requestImprovement","outputs":[],"payable":false,"stateMutability":"nonpayable","type":"function","signature":"0x00e979d9"},{"constant":false,"inputs":[{"internalType":"address","name":"_requester","type":"address"},{"internalType":"uint256","name":"_reward","type":"uint256"},{"internalType":"string","name":"_originalUrl","type":"string"}],"name":"requestTranslation","outputs":[],"payable":false,"stateMutability":"nonpayable","type":"function","signature":"0xc1a2aba3"},{"constant":false,"inputs":[{"internalType":"address","name":"_chftAddress","type":"address"}],"name":"setCHFTContract","outputs":[],"payable":false,"stateMutability":"nonpayable","type":"function","signature":"0xcef255f6"},{"constant":false,"inputs":[{"internalType":"address","name":"_translator","type":"address"},{"internalType":"uint256","name":"_value","type":"uint256"},{"internalType":"string","name":"_originalUrl","type":"string"},{"internalType":"string","name":"_translationUrl","type":"string"}],"name":"translationSubmission","outputs":[],"payable":false,"stateMutability":"nonpayable","type":"function","signature":"0x757b8ff5"},{"constant":false,"inputs":[{"internalType":"address","name":"_requester","type":"address"},{"internalType":"uint256","name":"_value","type":"uint256"},{"internalType":"string","name":"_originalUrl","type":"string"}],"name":"withdrawRequest","outputs":[],"payable":false,"stateMutability":"nonpayable","type":"function","signature":"0x86b3950c"}]